fcd_torch/ChemNet_v0.13_pretrained.pt
fcd_torch/__init__.py
fcd_torch/fcd.py
fcd_torch/keras2pytorch.py
fcd_torch/torch_layers.py
fcd_torch/utils.py
fcd_torch-1.0.7.dist-info/LICENSE
fcd_torch-1.0.7.dist-info/METADATA
fcd_torch-1.0.7.dist-info/WHEEL
fcd_torch-1.0.7.dist-info/top_level.txt
fcd_torch-1.0.7.dist-info/RECORD
