Metadata-Version: 2.1
Name: fcd-torch
Version: 1.0.7
Summary: Fréchet ChemNet Distance on PyTorch
Home-page: https://github.com/insilicomedicine/FCD_torch
Author: 
Author-email: 
License: MIT
Platform: UNKNOWN
Requires-Dist: torch
Requires-Dist: numpy
Requires-Dist: scipy
Provides-Extra: rdkit
Requires-Dist: rdkit ; extra == 'rdkit'
